zen/__init__.py
zen/__init__.pyi
zen/py.typed
zen/zen.cpython-310-aarch64-linux-gnu.so
zen_engine-0.51.0.dist-info/METADATA
zen_engine-0.51.0.dist-info/WHEEL
zen_engine-0.51.0.dist-info/entry_points.txt
zen_engine-0.51.0.dist-info/licenses/LICENSE
zen_engine-0.51.0.dist-info/RECORD
