Metadata-Version: 2.4
Name: zen-engine
Version: 0.51.0
Classifier: Programming Language :: Rust
Classifier: Programming Language :: Python :: Implementation :: CPython
Classifier: Programming Language :: Python :: Implementation :: PyPy
Requires-Dist: black ; extra == 'dev'
Requires-Dist: bumpver ; extra == 'dev'
Requires-Dist: isort ; extra == 'dev'
Requires-Dist: pip-tools ; extra == 'dev'
Requires-Dist: pytest ; extra == 'dev'
Requires-Dist: asyncio ; extra == 'dev'
Provides-Extra: dev
License-File: LICENSE
Summary: Open-Source Business Rules Engine
Keywords: gorules,zen-engine,business rules engine,rules engine,rule engine,bre,rule,rules,engine,decision,decision table,rust,pyo3
Author-email: GoRules Team <hi@gorules.io>
Requires-Python: >=3.7
Project-URL: Homepage, https://github.com/gorules/zen
